ext/__init__.py
ext/argsort.c
ext/argsort.cpython-36m-x86_64-linux-gnu.so
ext/example.c
ext/example.cpython-36m-x86_64-linux-gnu.so
ext/group_by.c
ext/group_by.cpython-36m-x86_64-linux-gnu.so
quick_pandas/__init__.py
quick_pandas/config.py
quick_pandas/dtypes.py
quick_pandas/main.py
quick_pandas/monkey.py
quick_pandas/np_funcs.py
quick_pandas/sort.py
quick_pandas/sort_api.py
quick_pandas/api/__init__.py
quick_pandas/api/pandas.py
quick_pandas/benchmark/__init__.py
quick_pandas/benchmark/groupby.py
quick_pandas/benchmark/pandas.py
quick_pandas/benchmark/radix_sort.py
quick_pandas/ext/__init__.py
quick_pandas/ext/argsort.c
quick_pandas/ext/argsort.cpython-36m-x86_64-linux-gnu.so
quick_pandas/ext/example.c
quick_pandas/ext/example.cpython-36m-x86_64-linux-gnu.so
quick_pandas/ext/group_by.c
quick_pandas/ext/group_by.cpython-36m-x86_64-linux-gnu.so
quick_pandas/wrappers/__init__.py
quick_pandas/wrappers/numpy_wrapper.py
quick_pandas/wrappers/pandas_wrapper.py
quick_pandas/wrappers/wrapper.py
quick_pandas/wrappers/pandas/__init__.py
quick_pandas/wrappers/pandas/groupby.py
quick_pandas-0.1.5.dist-info/LICENSE
quick_pandas-0.1.5.dist-info/METADATA
quick_pandas-0.1.5.dist-info/WHEEL
quick_pandas-0.1.5.dist-info/top_level.txt
quick_pandas-0.1.5.dist-info/RECORD
