Metadata-Version: 2.1
Name: quick-pandas
Version: 0.1.5
Summary: A monkey patch that makes pandas run faster
Home-page: https://github.com/johnson-li/fast-pandas
Author: Johnson Li
Author-email: johnsonli1993@gmail.com
License: MIT
Platform: Linux
Classifier: License :: OSI Approved :: MIT License
Classifier: Programming Language :: Python
Classifier: Programming Language :: Python :: 3
Classifier: Programming Language :: Python :: 3.6
Classifier: Programming Language :: Python :: 3.7
Classifier: Programming Language :: Python :: Implementation :: CPython
Classifier: Programming Language :: Python :: Implementation :: PyPy
Requires-Python: >=3.6.0
Requires-Dist: numba
Requires-Dist: numpy
Requires-Dist: pandas
